odoo10_addon_account_mass_reconcile_ref_deep_search-10.0.1.0.0.99.dev10-py3.8-nspkg.pth
odoo/addons/account_mass_reconcile_ref_deep_search/README.rst
odoo/addons/account_mass_reconcile_ref_deep_search/__init__.py
odoo/addons/account_mass_reconcile_ref_deep_search/__manifest__.py
odoo/addons/account_mass_reconcile_ref_deep_search/i18n/account_mass_reconcile_ref_deep_search.pot
odoo/addons/account_mass_reconcile_ref_deep_search/i18n/am.po
odoo/addons/account_mass_reconcile_ref_deep_search/i18n/ar.po
odoo/addons/account_mass_reconcile_ref_deep_search/i18n/bg.po
odoo/addons/account_mass_reconcile_ref_deep_search/i18n/bs.po
odoo/addons/account_mass_reconcile_ref_deep_search/i18n/ca.po
odoo/addons/account_mass_reconcile_ref_deep_search/i18n/ca_ES.po
odoo/addons/account_mass_reconcile_ref_deep_search/i18n/cs.po
odoo/addons/account_mass_reconcile_ref_deep_search/i18n/da.po
odoo/addons/account_mass_reconcile_ref_deep_search/i18n/de.po
odoo/addons/account_mass_reconcile_ref_deep_search/i18n/el_GR.po
odoo/addons/account_mass_reconcile_ref_deep_search/i18n/en_GB.po
odoo/addons/account_mass_reconcile_ref_deep_search/i18n/es.po
odoo/addons/account_mass_reconcile_ref_deep_search/i18n/es_AR.po
odoo/addons/account_mass_reconcile_ref_deep_search/i18n/es_CL.po
odoo/addons/account_mass_reconcile_ref_deep_search/i18n/es_CO.po
odoo/addons/account_mass_reconcile_ref_deep_search/i18n/es_CR.po
odoo/addons/account_mass_reconcile_ref_deep_search/i18n/es_DO.po
odoo/addons/account_mass_reconcile_ref_deep_search/i18n/es_EC.po
odoo/addons/account_mass_reconcile_ref_deep_search/i18n/es_ES.po
odoo/addons/account_mass_reconcile_ref_deep_search/i18n/es_MX.po
odoo/addons/account_mass_reconcile_ref_deep_search/i18n/es_PE.po
odoo/addons/account_mass_reconcile_ref_deep_search/i18n/es_PY.po
odoo/addons/account_mass_reconcile_ref_deep_search/i18n/es_VE.po
odoo/addons/account_mass_reconcile_ref_deep_search/i18n/et.po
odoo/addons/account_mass_reconcile_ref_deep_search/i18n/eu.po
odoo10_addon_account_mass_reconcile_ref_deep_search-10.0.1.0.0.99.dev10.dist-info/METADATA
odoo10_addon_account_mass_reconcile_ref_deep_search-10.0.1.0.0.99.dev10.dist-info/WHEEL
odoo10_addon_account_mass_reconcile_ref_deep_search-10.0.1.0.0.99.dev10.dist-info/namespace_packages.txt
odoo10_addon_account_mass_reconcile_ref_deep_search-10.0.1.0.0.99.dev10.dist-info/top_level.txt
odoo10_addon_account_mass_reconcile_ref_deep_search-10.0.1.0.0.99.dev10.dist-info/RECORD
